{
   "search_metadata" : {
      "completed_in" : 0.0510,
      "count" : 15,
      "max_id" : 428615284812161026,
      "max_id_str" : "428615284812161026",
      "next_results" : "?max_id=428615273663299583&q=cat&include_entities=1",
      "query" : "cat",
      "refresh_url" : "?since_id=428615284812161026&q=cat&include_entities=1",
      "since_id" : 0,
      "since_id_str" : "0"
   },
   "statuses" : [
      {
         "contributors" : null,
         "coordinates" : null,
         "created_at" : "Wed Jan 29 19:47:01 +0000 2014",
         "entities" : {
            "hashtags" : [],
            "symbols" : [],
            "urls" : [],
            "user_mentions" : []
         },
         "favorite_count" : 0,
         "favorited" : false,
         "geo" : null,
         "id" : 428615284812161026,
         "id_str" : "428615284812161026",
         "in_reply_to_screen_name" : null,
         "in_reply_to_status_id" : null,
         "in_reply_to_status_id_str" : null,
         "in_reply_to_user_id" : null,
         "in_reply_to_user_id_str" : null,
         "lang" : "en",
         "metadata" : {
            "iso_language_code" : "en",
            "result_type" : "recent"
         },
         "place" : null,
         "retweet_count" : 0,
         "retweeted" : false,
         "source" : "<a href=\"http://twitter.com/devices\" rel=\"nofollow\">txt</a>",
         "text" : "I have a cat scratch, repeat I have a cat scratch",
         "truncated" : false,
         "user" : {
            "contributors_enabled" : false,
            "created_at" : "Sat Aug 08 05:26:19 +0000 2009",
            "default_profile" : false,
            "default_profile_image" : false,
            "description" : "VHS. IG: twerkjuice. $tay gettin money in tha hood",
            "entities" : {
               "description" : {
                  "urls" : []
               }
            },
            "favourites_count" : 12,
            "follow_request_sent" : false,
            "followers_count" : 69,
            "following" : false,
            "friends_count" : 93,
            "geo_enabled" : true,
            "id" : 63914294,
            "id_str" : "63914294",
            "is_translation_enabled" : false,
            "is_translator" : false,
            "lang" : "en",
            "listed_count" : 0,
            "location" : "CALI",
            "name" : "Robey Rich",
            "notifications" : false,
            "profile_background_color" : "C0DEED",
            "profile_background_image_url" : "http://a0.twimg.com/profile_background_images/338705764/YOOOOOOO.jpg",
            "profile_background_image_url_https" : "https://si0.twimg.com/profile_background_images/338705764/YOOOOOOO.jpg",
            "profile_background_tile" : true,
            "profile_banner_url" : "https://pbs.twimg.com/profile_banners/63914294/1362385627",
            "profile_image_url" : "http://pbs.twimg.com/profile_images/3556559094/1de40bb82a1070d81ab5450a53525971_normal.jpeg",
            "profile_image_url_https" : "https://pbs.twimg.com/profile_images/3556559094/1de40bb82a1070d81ab5450a53525971_normal.jpeg",
            "profile_link_color" : "0084B4",
            "profile_sidebar_border_color" : "D60707",
            "profile_sidebar_fill_color" : "DDEEF6",
            "profile_text_color" : "333333",
            "profile_use_background_image" : true,
            "protected" : false,
            "screen_name" : "twerkjuice",
            "statuses_count" : 561,
            "time_zone" : "Pacific Time (US & Canada)",
            "url" : null,
            "utc_offset" : -28800,
            "verified" : false
         }
      },
      {
         "contributors" : null,
         "coordinates" : null,
         "created_at" : "Wed Jan 29 19:47:01 +0000 2014",
         "entities" : {
            "hashtags" : [],
            "media" : [
               {
                  "display_url" : "pic.twitter.com/MuXV2lKL1i",
                  "expanded_url" : "http://twitter.com/awkwardposts/status/427561642843709440/photo/1",
                  "id" : 427561642663374848,
                  "id_str" : "427561642663374848",
                  "indices" : [ 51, 73 ],
                  "media_url" : "http://pbs.twimg.com/media/Be8BDHaIcAANE-b.jpg",
                  "media_url_https" : "https://pbs.twimg.com/media/Be8BDHaIcAANE-b.jpg",
                  "sizes" : {
                     "large" : {
                        "h" : 600,
                        "resize" : "fit",
                        "w" : 500
                     },
                     "medium" : {
                        "h" : 600,
                        "resize" : "fit",
                        "w" : 500
                     },
                     "small" : {
                        "h" : 408,
                        "resize" : "fit",
                        "w" : 340
                     },
                     "thumb" : {
                        "h" : 150,
                        "resize" : "crop",
                        "w" : 150
                     }
                  },
                  "source_status_id" : 427561642843709440,
                  "source_status_id_str" : "427561642843709440",
                  "type" : "photo",
                  "url" : "http://t.co/MuXV2lKL1i"
               }
            ],
            "symbols" : [],
            "urls" : [],
            "user_mentions" : [
               {
                  "id" : 390860562,
                  "id_str" : "390860562",
                  "indices" : [ 1, 14 ],
                  "name" : "Awkward Posts",
                  "screen_name" : "awkwardposts"
               }
            ]
         },
         "favorite_count" : 0,
         "favorited" : false,
         "geo" : null,
         "id" : 428615284442689536,
         "id_str" : "428615284442689536",
         "in_reply_to_screen_name" : "awkwardposts",
         "in_reply_to_status_id" : 427561642843709440,
         "in_reply_to_status_id_str" : "427561642843709440",
         "in_reply_to_user_id" : 390860562,
         "in_reply_to_user_id_str" : "390860562",
         "lang" : "en",
         "metadata" : {
            "iso_language_code" : "en",
            "result_type" : "recent"
         },
         "place" : null,
         "possibly_sensitive" : false,
         "retweet_count" : 0,
         "retweeted" : false,
         "source" : "<a href=\"http://twitter.com/download/iphone\" rel=\"nofollow\">Twitter for iPhone</a>",
         "text" : "“@awkwardposts: This cat has better eyes than me 💙 http://t.co/MuXV2lKL1i” Pure beauty.",
         "truncated" : false,
         "user" : {
            "contributors_enabled" : false,
            "created_at" : "Tue Sep 25 21:04:21 +0000 2012",
            "default_profile" : false,
            "default_profile_image" : false,
            "description" : "Nothing is real until it's gone.",
            "entities" : {
               "description" : {
                  "urls" : []
               }
            },
            "favourites_count" : 8340,
            "follow_request_sent" : false,
            "followers_count" : 280,
            "following" : false,
            "friends_count" : 310,
            "geo_enabled" : false,
            "id" : 846221670,
            "id_str" : "846221670",
            "is_translation_enabled" : false,
            "is_translator" : false,
            "lang" : "en",
            "listed_count" : 0,
            "location" : "",
            "name" : "Reger's Girl✨",
            "notifications" : false,
            "profile_background_color" : "1A1B1F",
            "profile_background_image_url" : "http://a0.twimg.com/profile_background_images/756387742/2acc9a7a38e0a84ca447a4478df8f23f.jpeg",
            "profile_background_image_url_https" : "https://si0.twimg.com/profile_background_images/756387742/2acc9a7a38e0a84ca447a4478df8f23f.jpeg",
            "profile_background_tile" : true,
            "profile_banner_url" : "https://pbs.twimg.com/profile_banners/846221670/1389652921",
            "profile_image_url" : "http://pbs.twimg.com/profile_images/418580506348109824/1-l7SqPo_normal.jpeg",
            "profile_image_url_https" : "https://pbs.twimg.com/profile_images/418580506348109824/1-l7SqPo_normal.jpeg",
            "profile_link_color" : "2FC2EF",
            "profile_sidebar_border_color" : "FFFFFF",
            "profile_sidebar_fill_color" : "DDEEF6",
            "profile_text_color" : "333333",
            "profile_use_background_image" : true,
            "protected" : false,
            "screen_name" : "Dayee97",
            "statuses_count" : 13999,
            "time_zone" : null,
            "url" : null,
            "utc_offset" : null,
            "verified" : false
         }
      },
      {
         "contributors" : null,
         "coordinates" : null,
         "created_at" : "Wed Jan 29 19:47:01 +0000 2014",
         "entities" : {
            "hashtags" : [],
            "symbols" : [],
            "urls" : [
               {
                  "display_url" : "ow.ly/3ACZu",
                  "expanded_url" : "http://ow.ly/3ACZu",
                  "indices" : [ 43, 65 ],
                  "url" : "http://t.co/V1NL9wMirP"
               }
            ],
            "user_mentions" : []
         },
         "favorite_count" : 0,
         "favorited" : false,
         "geo" : null,
         "id" : 428615283830292480,
         "id_str" : "428615283830292480",
         "in_reply_to_screen_name" : null,
         "in_reply_to_status_id" : null,
         "in_reply_to_status_id_str" : null,
         "in_reply_to_user_id" : null,
         "in_reply_to_user_id_str" : null,
         "lang" : "ja",
         "metadata" : {
            "iso_language_code" : "ja",
            "result_type" : "recent"
         },
         "place" : null,
         "possibly_sensitive" : false,
         "retweet_count" : 0,
         "retweeted" : false,
         "source" : "<a href=\"http://twittbot.net/\" rel=\"nofollow\">twittbot.net</a>",
         "text" : "【メルぞう・みーと流】売り込みゼロのメルマガを運営して毎月３万円の収入を得る方法です!http://t.co/V1NL9wMirP #followmeJP#toushi#konbanwa#okane#fukusyunyu#affiliatejp",
         "truncated" : false,
         "user" : {
            "contributors_enabled" : false,
            "created_at" : "Sun Jan 09 07:21:52 +0000 2011",
            "default_profile" : true,
            "default_profile_image" : true,
            "description" : "",
            "entities" : {
               "description" : {
                  "urls" : []
               }
            },
            "favourites_count" : 0,
            "follow_request_sent" : false,
            "followers_count" : 358,
            "following" : false,
            "friends_count" : 1,
            "geo_enabled" : false,
            "id" : 235864485,
            "id_str" : "235864485",
            "is_translation_enabled" : false,
            "is_translator" : false,
            "lang" : "ja",
            "listed_count" : 4,
            "location" : "",
            "name" : "アフィリツール",
            "notifications" : false,
            "profile_background_color" : "C0DEED",
            "profile_background_image_url" : "http://abs.twimg.com/images/themes/theme1/bg.png",
            "profile_background_image_url_https" : "https://abs.twimg.com/images/themes/theme1/bg.png",
            "profile_background_tile" : false,
            "profile_image_url" : "http://abs.twimg.com/sticky/default_profile_images/default_profile_3_normal.png",
            "profile_image_url_https" : "https://abs.twimg.com/sticky/default_profile_images/default_profile_3_normal.png",
            "profile_link_color" : "0084B4",
            "profile_sidebar_border_color" : "C0DEED",
            "profile_sidebar_fill_color" : "DDEEF6",
            "profile_text_color" : "333333",
            "profile_use_background_image" : true,
            "protected" : false,
            "screen_name" : "brogaf",
            "statuses_count" : 48420,
            "time_zone" : "Hawaii",
            "url" : null,
            "utc_offset" : -36000,
            "verified" : false
         }
      },
      {
         "contributors" : null,
         "coordinates" : null,
         "created_at" : "Wed Jan 29 19:47:01 +0000 2014",
         "entities" : {
            "hashtags" : [],
            "symbols" : [],
            "urls" : [],
            "user_mentions" : []
         },
         "favorite_count" : 0,
         "favorited" : false,
         "geo" : null,
         "id" : 428615282815295488,
         "id_str" : "428615282815295488",
         "in_reply_to_screen_name" : null,
         "in_reply_to_status_id" : null,
         "in_reply_to_status_id_str" : null,
         "in_reply_to_user_id" : null,
         "in_reply_to_user_id_str" : null,
         "lang" : "en",
         "metadata" : {
            "iso_language_code" : "en",
            "result_type" : "recent"
         },
         "place" : null,
         "retweet_count" : 0,
         "retweeted" : false,
         "source" : "web",
         "text" : "cat owner problems",
         "truncated" : false,
         "user" : {
            "contributors_enabled" : false,
            "created_at" : "Tue Feb 09 22:27:10 +0000 2010",
            "default_profile" : false,
            "default_profile_image" : false,
            "description" : "I never was. I am.",
            "entities" : {
               "description" : {
                  "urls" : []
               }
            },
            "favourites_count" : 7116,
            "follow_request_sent" : false,
            "followers_count" : 971,
            "following" : false,
            "friends_count" : 177,
            "geo_enabled" : false,
            "id" : 112849196,
            "id_str" : "112849196",
            "is_translation_enabled" : false,
            "is_translator" : false,
            "lang" : "en",
            "listed_count" : 6,
            "location" : "dimension 7",
            "name" : "☻",
            "notifications" : false,
            "profile_background_color" : "242124",
            "profile_background_image_url" : "http://a0.twimg.com/profile_background_images/378800000152193836/k5PKx0PW.jpeg",
            "profile_background_image_url_https" : "https://si0.twimg.com/profile_background_images/378800000152193836/k5PKx0PW.jpeg",
            "profile_background_tile" : true,
            "profile_banner_url" : "https://pbs.twimg.com/profile_banners/112849196/1390713436",
            "profile_image_url" : "http://pbs.twimg.com/profile_images/426512806360264705/dCttw1cA_normal.jpeg",
            "profile_image_url_https" : "https://pbs.twimg.com/profile_images/426512806360264705/dCttw1cA_normal.jpeg",
            "profile_link_color" : "4D0B22",
            "profile_sidebar_border_color" : "000000",
            "profile_sidebar_fill_color" : "000000",
            "profile_text_color" : "0ABEFF",
            "profile_use_background_image" : true,
            "protected" : false,
            "screen_name" : "GoldDustAlien",
            "statuses_count" : 34487,
            "time_zone" : "Eastern Time (US & Canada)",
            "url" : null,
            "utc_offset" : -18000,
            "verified" : false
         }
      },
      {
         "contributors" : null,
         "coordinates" : null,
         "created_at" : "Wed Jan 29 19:47:01 +0000 2014",
         "entities" : {
            "hashtags" : [],
            "symbols" : [],
            "urls" : [],
            "user_mentions" : [
               {
                  "id" : 41956730,
                  "id_str" : "41956730",
                  "indices" : [ 0, 11 ],
                  "name" : "magisco",
                  "screen_name" : "itsNABISCO"
               }
            ]
         },
         "favorite_count" : 0,
         "favorited" : false,
         "geo" : null,
         "id" : 428615282165559296,
         "id_str" : "428615282165559296",
         "in_reply_to_screen_name" : "itsNABISCO",
         "in_reply_to_status_id" : 428614954309394432,
         "in_reply_to_status_id_str" : "428614954309394432",
         "in_reply_to_user_id" : 41956730,
         "in_reply_to_user_id_str" : "41956730",
         "lang" : "it",
         "metadata" : {
            "iso_language_code" : "it",
            "result_type" : "recent"
         },
         "place" : null,
         "retweet_count" : 0,
         "retweeted" : false,
         "source" : "<a href=\"http://twitter.com/download/iphone\" rel=\"nofollow\">Twitter for iPhone</a>",
         "text" : "@itsNABISCO letisco",
         "truncated" : false,
         "user" : {
            "contributors_enabled" : false,
            "created_at" : "Thu Mar 04 03:52:30 +0000 2010",
            "default_profile" : false,
            "default_profile_image" : false,
            "description" : "um quadro de da vinci escrito vem todo mundo se fude (sempre amanheço flôr)",
            "entities" : {
               "description" : {
                  "urls" : []
               },
               "url" : {
                  "urls" : [
                     {
                        "display_url" : "twitter.com/gabrielecosta/…",
                        "expanded_url" : "https://twitter.com/gabrielecosta/status/410261907573334016",
                        "indices" : [ 0, 23 ],
                        "url" : "https://t.co/zN1ySZWCo7"
                     }
                  ]
               }
            },
            "favourites_count" : 24539,
            "follow_request_sent" : false,
            "followers_count" : 455,
            "following" : false,
            "friends_count" : 394,
            "geo_enabled" : false,
            "id" : 119607510,
            "id_str" : "119607510",
            "is_translation_enabled" : false,
            "is_translator" : false,
            "lang" : "en",
            "listed_count" : 21,
            "location" : "markarth",
            "name" : "vândalo assange",
            "notifications" : false,
            "profile_background_color" : "FFFFFF",
            "profile_background_image_url" : "http://a0.twimg.com/profile_background_images/378800000008146242/f57b6aae54bb25252357f264900bd6bf.png",
            "profile_background_image_url_https" : "https://si0.twimg.com/profile_background_images/378800000008146242/f57b6aae54bb25252357f264900bd6bf.png",
            "profile_background_tile" : true,
            "profile_banner_url" : "https://pbs.twimg.com/profile_banners/119607510/1369801342",
            "profile_image_url" : "http://pbs.twimg.com/profile_images/378800000607925903/32ab5e0a1808662d51fcf695488c88b9_normal.png",
            "profile_image_url_https" : "https://pbs.twimg.com/profile_images/378800000607925903/32ab5e0a1808662d51fcf695488c88b9_normal.png",
            "profile_link_color" : "FF0000",
            "profile_sidebar_border_color" : "000000",
            "profile_sidebar_fill_color" : "DDEEF6",
            "profile_text_color" : "333333",
            "profile_use_background_image" : true,
            "protected" : false,
            "screen_name" : "renyan_cat",
            "statuses_count" : 85824,
            "time_zone" : "Greenland",
            "url" : "https://t.co/zN1ySZWCo7",
            "utc_offset" : -10800,
            "verified" : false
         }
      },
      {
         "contributors" : null,
         "coordinates" : null,
         "created_at" : "Wed Jan 29 19:47:01 +0000 2014",
         "entities" : {
            "hashtags" : [],
            "symbols" : [],
            "urls" : [],
            "user_mentions" : [
               {
                  "id" : 1300365626,
                  "id_str" : "1300365626",
                  "indices" : [ 0, 14 ],
                  "name" : "d y i n g † ",
                  "screen_name" : "imjustbroken_"
               }
            ]
         },
         "favorite_count" : 0,
         "favorited" : false,
         "geo" : null,
         "id" : 428615281439944705,
         "id_str" : "428615281439944705",
         "in_reply_to_screen_name" : "imjustbroken_",
         "in_reply_to_status_id" : 428615081984000000,
         "in_reply_to_status_id_str" : "428615081984000000",
         "in_reply_to_user_id" : 1300365626,
         "in_reply_to_user_id_str" : "1300365626",
         "lang" : "fr",
         "metadata" : {
            "iso_language_code" : "fr",
            "result_type" : "recent"
         },
         "place" : null,
         "retweet_count" : 0,
         "retweeted" : false,
         "source" : "<a href=\"http://twitter.com/download/iphone\" rel=\"nofollow\">Twitter for iPhone</a>",
         "text" : "@imjustbroken_ Cat est une salope qu'il va falloir oublier bby.",
         "truncated" : false,
         "user" : {
            "contributors_enabled" : false,
            "created_at" : "Sun Mar 24 13:19:47 +0000 2013",
            "default_profile" : true,
            "default_profile_image" : false,
            "description" : "L'enfer qu'est la vie me consume peu à peu.",
            "entities" : {
               "description" : {
                  "urls" : []
               },
               "url" : {
                  "urls" : [
                     {
                        "display_url" : "ask.fm/hatemyfatbody",
                        "expanded_url" : "http://ask.fm/hatemyfatbody",
                        "indices" : [ 0, 22 ],
                        "url" : "http://t.co/yyAazedLnN"
                     }
                  ]
               }
            },
            "favourites_count" : 1115,
            "follow_request_sent" : false,
            "followers_count" : 1348,
            "following" : false,
            "friends_count" : 140,
            "geo_enabled" : true,
            "id" : 1295255455,
            "id_str" : "1295255455",
            "is_translation_enabled" : false,
            "is_translator" : false,
            "lang" : "fr",
            "listed_count" : 4,
            "location" : "",
            "name" : "survivor",
            "notifications" : false,
            "profile_background_color" : "C0DEED",
            "profile_background_image_url" : "http://abs.twimg.com/images/themes/theme1/bg.png",
            "profile_background_image_url_https" : "https://abs.twimg.com/images/themes/theme1/bg.png",
            "profile_background_tile" : false,
            "profile_banner_url" : "https://pbs.twimg.com/profile_banners/1295255455/1389535685",
            "profile_image_url" : "http://pbs.twimg.com/profile_images/422490211969695744/Lm9BtNoK_normal.jpeg",
            "profile_image_url_https" : "https://pbs.twimg.com/profile_images/422490211969695744/Lm9BtNoK_normal.jpeg",
            "profile_link_color" : "0084B4",
            "profile_sidebar_border_color" : "C0DEED",
            "profile_sidebar_fill_color" : "DDEEF6",
            "profile_text_color" : "333333",
            "profile_use_background_image" : true,
            "protected" : false,
            "screen_name" : "societykillme",
            "statuses_count" : 9897,
            "time_zone" : "Athens",
            "url" : "http://t.co/yyAazedLnN",
            "utc_offset" : 7200,
            "verified" : false
         }
      },
      {
         "contributors" : null,
         "coordinates" : null,
         "created_at" : "Wed Jan 29 19:47:00 +0000 2014",
         "entities" : {
            "hashtags" : [],
            "media" : [
               {
                  "display_url" : "pic.twitter.com/LfHHCZjavk",
                  "expanded_url" : "http://twitter.com/devengreves/status/428615281238233088/photo/1",
                  "id" : 428615280877527040,
                  "id_str" : "428615280877527040",
                  "indices" : [ 71, 93 ],
                  "media_url" : "http://pbs.twimg.com/media/BfK_U7oCYAA7eTi.jpg",
                  "media_url_https" : "https://pbs.twimg.com/media/BfK_U7oCYAA7eTi.jpg",
                  "sizes" : {
                     "large" : {
                        "h" : 1810,
                        "resize" : "fit",
                        "w" : 1024
                     },
                     "medium" : {
                        "h" : 1061,
                        "resize" : "fit",
                        "w" : 600
                     },
                     "small" : {
                        "h" : 601,
                        "resize" : "fit",
                        "w" : 340
                     },
                     "thumb" : {
                        "h" : 150,
                        "resize" : "crop",
                        "w" : 150
                     }
                  },
                  "type" : "photo",
                  "url" : "http://t.co/LfHHCZjavk"
               }
            ],
            "symbols" : [],
            "urls" : [],
            "user_mentions" : []
         },
         "favorite_count" : 0,
         "favorited" : false,
         "geo" : null,
         "id" : 428615281238233088,
         "id_str" : "428615281238233088",
         "in_reply_to_screen_name" : null,
         "in_reply_to_status_id" : null,
         "in_reply_to_status_id_str" : null,
         "in_reply_to_user_id" : null,
         "in_reply_to_user_id_str" : null,
         "lang" : "en",
         "metadata" : {
            "iso_language_code" : "en",
            "result_type" : "recent"
         },
         "place" : null,
         "possibly_sensitive" : false,
         "retweet_count" : 0,
         "retweeted" : false,
         "source" : "<a href=\"http://janetter.net/\" rel=\"nofollow\">Janetter Pro for Android</a>",
         "text" : "Here in the Greves household, we practice extreme cat house insulation http://t.co/LfHHCZjavk",
         "truncated" : false,
         "user" : {
            "contributors_enabled" : false,
            "created_at" : "Tue Oct 02 21:32:56 +0000 2007",
            "default_profile" : false,
            "default_profile_image" : false,
            "description" : "Canadian person who draws stuff. devengreves@gmail",
            "entities" : {
               "description" : {
                  "urls" : []
               },
               "url" : {
                  "urls" : [
                     {
                        "display_url" : "devengreves.com",
                        "expanded_url" : "http://www.devengreves.com",
                        "indices" : [ 0, 22 ],
                        "url" : "http://t.co/auJTdtLCy3"
                     }
                  ]
               }
            },
            "favourites_count" : 160,
            "follow_request_sent" : false,
            "followers_count" : 49,
            "following" : false,
            "friends_count" : 78,
            "geo_enabled" : false,
            "id" : 9214232,
            "id_str" : "9214232",
            "is_translation_enabled" : false,
            "is_translator" : false,
            "lang" : "en",
            "listed_count" : 1,
            "location" : "Canada",
            "name" : "Deven Greves",
            "notifications" : false,
            "profile_background_color" : "FF6699",
            "profile_background_image_url" : "http://abs.twimg.com/images/themes/theme11/bg.gif",
            "profile_background_image_url_https" : "https://abs.twimg.com/images/themes/theme11/bg.gif",
            "profile_background_tile" : true,
            "profile_banner_url" : "https://pbs.twimg.com/profile_banners/9214232/1386785299",
            "profile_image_url" : "http://pbs.twimg.com/profile_images/426513342258110464/J0M6bwNC_normal.jpeg",
            "profile_image_url_https" : "https://pbs.twimg.com/profile_images/426513342258110464/J0M6bwNC_normal.jpeg",
            "profile_link_color" : "B40B43",
            "profile_sidebar_border_color" : "CC3366",
            "profile_sidebar_fill_color" : "E5507E",
            "profile_text_color" : "362720",
            "profile_use_background_image" : true,
            "protected" : false,
            "screen_name" : "devengreves",
            "statuses_count" : 4130,
            "time_zone" : "Eastern Time (US & Canada)",
            "url" : "http://t.co/auJTdtLCy3",
            "utc_offset" : -18000,
            "verified" : false
         }
      },
      {
         "contributors" : null,
         "coordinates" : null,
         "created_at" : "Wed Jan 29 19:47:00 +0000 2014",
         "entities" : {
            "hashtags" : [],
            "symbols" : [],
            "urls" : [],
            "user_mentions" : [
               {
                  "id" : 347186102,
                  "id_str" : "347186102",
                  "indices" : [ 3, 11 ],
                  "name" : "Dori la exploradori",
                  "screen_name" : "eli_txu"
               },
               {
                  "id" : 234078790,
                  "id_str" : "234078790",
                  "indices" : [ 13, 22 ],
                  "name" : "Miss Nothing ✘✘✘✘  ",
                  "screen_name" : "Irune_HS"
               }
            ]
         },
         "favorite_count" : 0,
         "favorited" : false,
         "geo" : null,
         "id" : 428615280643018752,
         "id_str" : "428615280643018752",
         "in_reply_to_screen_name" : null,
         "in_reply_to_status_id" : null,
         "in_reply_to_status_id_str" : null,
         "in_reply_to_user_id" : null,
         "in_reply_to_user_id_str" : null,
         "lang" : "en",
         "metadata" : {
            "iso_language_code" : "en",
            "result_type" : "recent"
         },
         "place" : null,
         "retweet_count" : 1,
         "retweeted" : false,
         "retweeted_status" : {
            "contributors" : null,
            "coordinates" : null,
            "created_at" : "Wed Jan 29 19:32:39 +0000 2014",
            "entities" : {
               "hashtags" : [],
               "symbols" : [],
               "urls" : [],
               "user_mentions" : [
                  {
                     "id" : 234078790,
                     "id_str" : "234078790",
                     "indices" : [ 0, 9 ],
                     "name" : "Miss Nothing ✘✘✘✘  ",
                     "screen_name" : "Irune_HS"
                  }
               ]
            },
            "favorite_count" : 0,
            "favorited" : false,
            "geo" : null,
            "id" : 428611667749265408,
            "id_str" : "428611667749265408",
            "in_reply_to_screen_name" : "Irune_HS",
            "in_reply_to_status_id" : 428602867017330689,
            "in_reply_to_status_id_str" : "428602867017330689",
            "in_reply_to_user_id" : 234078790,
            "in_reply_to_user_id_str" : "234078790",
            "lang" : "en",
            "metadata" : {
               "iso_language_code" : "en",
               "result_type" : "recent"
            },
            "place" : null,
            "retweet_count" : 1,
            "retweeted" : false,
            "source" : "<a href=\"http://twitter.com/download/android\" rel=\"nofollow\">Twitter for Android</a>",
            "text" : "@Irune_HS zombie cat. Im so bored.",
            "truncated" : false,
            "user" : {
               "contributors_enabled" : false,
               "created_at" : "Tue Aug 02 12:05:30 +0000 2011",
               "default_profile" : false,
               "default_profile_image" : false,
               "description" : "Nivel 20. Stranger in a strange land. Zombie, gamer, echelon,A7X, ADTR, MCR, BFMV, TDG.. Podría seguir pero no acabaría en un buen rato.",
               "entities" : {
                  "description" : {
                     "urls" : []
                  },
                  "url" : {
                     "urls" : [
                        {
                           "display_url" : "ask.fm/eliena",
                           "expanded_url" : "http://ask.fm/eliena",
                           "indices" : [ 0, 22 ],
                           "url" : "http://t.co/DFy3TKnvTB"
                        }
                     ]
                  }
               },
               "favourites_count" : 150,
               "follow_request_sent" : false,
               "followers_count" : 695,
               "following" : false,
               "friends_count" : 727,
               "geo_enabled" : true,
               "id" : 347186102,
               "id_str" : "347186102",
               "is_translation_enabled" : false,
               "is_translator" : false,
               "lang" : "es",
               "listed_count" : 4,
               "location" : "Bilbao",
               "name" : "Dori la exploradori",
               "notifications" : false,
               "profile_background_color" : "1A1B1F",
               "profile_background_image_url" : "http://a0.twimg.com/profile_background_images/734972030/34a9d2ac8dab2433cd2d0ee21e02afab.jpeg",
               "profile_background_image_url_https" : "https://si0.twimg.com/profile_background_images/734972030/34a9d2ac8dab2433cd2d0ee21e02afab.jpeg",
               "profile_background_tile" : true,
               "profile_banner_url" : "https://pbs.twimg.com/profile_banners/347186102/1369221260",
               "profile_image_url" : "http://pbs.twimg.com/profile_images/418019851803045888/zqcjdic1_normal.jpeg",
               "profile_image_url_https" : "https://pbs.twimg.com/profile_images/418019851803045888/zqcjdic1_normal.jpeg",
               "profile_link_color" : "2FC2EF",
               "profile_sidebar_border_color" : "FFFFFF",
               "profile_sidebar_fill_color" : "252429",
               "profile_text_color" : "666666",
               "profile_use_background_image" : true,
               "protected" : false,
               "screen_name" : "eli_txu",
               "statuses_count" : 4527,
               "time_zone" : null,
               "url" : "http://t.co/DFy3TKnvTB",
               "utc_offset" : null,
               "verified" : false
            }
         },
         "source" : "<a href=\"http://twitter.com/download/android\" rel=\"nofollow\">Twitter for Android</a>",
         "text" : "RT @eli_txu: @Irune_HS zombie cat. Im so bored.",
         "truncated" : false,
         "user" : {
            "contributors_enabled" : false,
            "created_at" : "Tue Jan 04 20:09:55 +0000 2011",
            "default_profile" : false,
            "default_profile_image" : false,
            "description" : "Ander Herrera |ATHLETIC ALA HIL| [5/6/2013] Sora♡Kairi /Gamer/ I'm a zombie†.TPR.Paramore.A Day To Remember.Tonight Alive.Little black star [Smile and be a cat]",
            "entities" : {
               "description" : {
                  "urls" : []
               },
               "url" : {
                  "urls" : [
                     {
                        "display_url" : "irucat.tumblr.com",
                        "expanded_url" : "http://irucat.tumblr.com/",
                        "indices" : [ 0, 22 ],
                        "url" : "http://t.co/xu9sNFENsl"
                     }
                  ]
               }
            },
            "favourites_count" : 3160,
            "follow_request_sent" : false,
            "followers_count" : 691,
            "following" : false,
            "friends_count" : 682,
            "geo_enabled" : true,
            "id" : 234078790,
            "id_str" : "234078790",
            "is_translation_enabled" : false,
            "is_translator" : false,
            "lang" : "eu",
            "listed_count" : 7,
            "location" : "Gryffindor|Bilbao",
            "name" : "Miss Nothing ✘✘✘✘  ",
            "notifications" : false,
            "profile_background_color" : "FFFFFF",
            "profile_background_image_url" : "http://a0.twimg.com/profile_background_images/378800000165805609/IdrSKmxH.jpeg",
            "profile_background_image_url_https" : "https://si0.twimg.com/profile_background_images/378800000165805609/IdrSKmxH.jpeg",
            "profile_background_tile" : true,
            "profile_banner_url" : "https://pbs.twimg.com/profile_banners/234078790/1390645682",
            "profile_image_url" : "http://pbs.twimg.com/profile_images/378800000447555928/8fce2ba2549b4958ac8135d1781a662a_normal.jpeg",
            "profile_image_url_https" : "https://pbs.twimg.com/profile_images/378800000447555928/8fce2ba2549b4958ac8135d1781a662a_normal.jpeg",
            "profile_link_color" : "E67CA7",
            "profile_sidebar_border_color" : "FFFFFF",
            "profile_sidebar_fill_color" : "252429",
            "profile_text_color" : "666666",
            "profile_use_background_image" : true,
            "protected" : false,
            "screen_name" : "Irune_HS",
            "statuses_count" : 14815,
            "time_zone" : "Madrid",
            "url" : "http://t.co/xu9sNFENsl",
            "utc_offset" : 3600,
            "verified" : false
         }
      },
      {
         "contributors" : null,
         "coordinates" : null,
         "created_at" : "Wed Jan 29 19:47:00 +0000 2014",
         "entities" : {
            "hashtags" : [
               {
                  "indices" : [ 129, 132 ],
                  "text" : "AH"
               }
            ],
            "symbols" : [],
            "urls" : [
               {
                  "display_url" : "centrodeestudiosandaluces.es/?mod=actividad…",
                  "expanded_url" : "http://www.centrodeestudiosandaluces.es/?mod=actividades&id=2711&cat=22&idm=",
                  "indices" : [ 139, 140 ],
                  "url" : "http://t.co/FkUaaUgeUu"
               }
            ],
            "user_mentions" : [
               {
                  "id" : 533125840,
                  "id_str" : "533125840",
                  "indices" : [ 3, 15 ],
                  "name" : "C.Estudios Andaluces",
                  "screen_name" : "CEAndaluces"
               }
            ]
         },
         "favorite_count" : 0,
         "favorited" : false,
         "geo" : null,
         "id" : 428615280160686081,
         "id_str" : "428615280160686081",
         "in_reply_to_screen_name" : null,
         "in_reply_to_status_id" : null,
         "in_reply_to_status_id_str" : null,
         "in_reply_to_user_id" : null,
         "in_reply_to_user_id_str" : null,
         "lang" : "es",
         "metadata" : {
            "iso_language_code" : "es",
            "result_type" : "recent"
         },
         "place" : null,
         "possibly_sensitive" : false,
         "retweet_count" : 4,
         "retweeted" : false,
         "retweeted_status" : {
            "contributors" : null,
            "coordinates" : null,
            "created_at" : "Tue Jan 28 21:42:34 +0000 2014",
            "entities" : {
               "hashtags" : [
                  {
                     "indices" : [ 112, 115 ],
                     "text" : "AH"
                  }
               ],
               "symbols" : [],
               "urls" : [
                  {
                     "display_url" : "centrodeestudiosandaluces.es/?mod=actividad…",
                     "expanded_url" : "http://www.centrodeestudiosandaluces.es/?mod=actividades&id=2711&cat=22&idm=",
                     "indices" : [ 117, 139 ],
                     "url" : "http://t.co/FkUaaUgeUu"
                  }
               ],
               "user_mentions" : []
            },
            "favorite_count" : 1,
            "favorited" : false,
            "geo" : null,
            "id" : 428281976533970944,
            "id_str" : "428281976533970944",
            "in_reply_to_screen_name" : null,
            "in_reply_to_status_id" : null,
            "in_reply_to_status_id_str" : null,
            "in_reply_to_user_id" : null,
            "in_reply_to_user_id_str" : null,
            "lang" : "es",
            "metadata" : {
               "iso_language_code" : "es",
               "result_type" : "recent"
            },
            "place" : null,
            "possibly_sensitive" : false,
            "retweet_count" : 4,
            "retweeted" : false,
            "source" : "<a href=\"http://twitter.com/tweetbutton\" rel=\"nofollow\">Tweet Button</a>",
            "text" : "El Museo de la Autonomía acoge una exposición sobre el exilio republicano y presenta el último nº de la revista #AH  http://t.co/FkUaaUgeUu",
            "truncated" : false,
            "user" : {
               "contributors_enabled" : false,
               "created_at" : "Thu Mar 22 13:10:03 +0000 2012",
               "default_profile" : false,
               "default_profile_image" : false,
               "description" : "La Fundación Centro de Estudios Andaluces persigue el fomento de la investigación, la formación y el impulso de iniciativas de conocimiento sobre Andalucía.",
               "entities" : {
                  "description" : {
                     "urls" : []
                  },
                  "url" : {
                     "urls" : [
                        {
                           "display_url" : "centrodeestudiosandaluces.es",
                           "expanded_url" : "http://www.centrodeestudiosandaluces.es",
                           "indices" : [ 0, 22 ],
                           "url" : "http://t.co/pIdY7Labvr"
                        }
                     ]
                  }
               },
               "favourites_count" : 134,
               "follow_request_sent" : false,
               "followers_count" : 937,
               "following" : false,
               "friends_count" : 502,
               "geo_enabled" : true,
               "id" : 533125840,
               "id_str" : "533125840",
               "is_translation_enabled" : false,
               "is_translator" : false,
               "lang" : "es",
               "listed_count" : 43,
               "location" : "C/ Bailén, 50. 41001. Sevilla",
               "name" : "C.Estudios Andaluces",
               "notifications" : false,
               "profile_background_color" : "C0DEED",
               "profile_background_image_url" : "http://a0.twimg.com/profile_background_images/378800000071114663/63dc9b3705d5dea5a6a60daf4390dfbf.jpeg",
               "profile_background_image_url_https" : "https://si0.twimg.com/profile_background_images/378800000071114663/63dc9b3705d5dea5a6a60daf4390dfbf.jpeg",
               "profile_background_tile" : false,
               "profile_image_url" : "http://pbs.twimg.com/profile_images/378800000438361417/d3dc21572cbb9725245944b36b6374b0_normal.jpeg",
               "profile_image_url_https" : "https://pbs.twimg.com/profile_images/378800000438361417/d3dc21572cbb9725245944b36b6374b0_normal.jpeg",
               "profile_link_color" : "0084B4",
               "profile_sidebar_border_color" : "FFFFFF",
               "profile_sidebar_fill_color" : "DDEEF6",
               "profile_text_color" : "333333",
               "profile_use_background_image" : true,
               "protected" : false,
               "screen_name" : "CEAndaluces",
               "statuses_count" : 1886,
               "time_zone" : "Amsterdam",
               "url" : "http://t.co/pIdY7Labvr",
               "utc_offset" : 3600,
               "verified" : false
            }
         },
         "source" : "<a href=\"http://twitter.com/download/android\" rel=\"nofollow\">Twitter for Android</a>",
         "text" : "RT @CEAndaluces: El Museo de la Autonomía acoge una exposición sobre el exilio republicano y presenta el último nº de la revista #AH  http:…",
         "truncated" : false,
         "user" : {
            "contributors_enabled" : false,
            "created_at" : "Sun Oct 23 19:45:08 +0000 2011",
            "default_profile" : false,
            "default_profile_image" : false,
            "description" : "Creí ser único, pero espero que tú lo seas más que yo. NDDA G",
            "entities" : {
               "description" : {
                  "urls" : []
               }
            },
            "favourites_count" : 1298,
            "follow_request_sent" : false,
            "followers_count" : 122,
            "following" : false,
            "friends_count" : 163,
            "geo_enabled" : true,
            "id" : 396797072,
            "id_str" : "396797072",
            "is_translation_enabled" : false,
            "is_translator" : false,
            "lang" : "es",
            "listed_count" : 1,
            "location" : "ρυєвℓα δεl 尺ιø, ѕєνιℓℓα. Es ",
            "name" : "J๏รє Ѕαℓgα∂σ ツ",
            "notifications" : false,
            "profile_background_color" : "C0DEED",
            "profile_background_image_url" : "http://a0.twimg.com/profile_background_images/529972440/fondo.jpg",
            "profile_background_image_url_https" : "https://si0.twimg.com/profile_background_images/529972440/fondo.jpg",
            "profile_background_tile" : false,
            "profile_banner_url" : "https://pbs.twimg.com/profile_banners/396797072/1390832307",
            "profile_image_url" : "http://pbs.twimg.com/profile_images/427905238214144001/_QvjSvGl_normal.jpeg",
            "profile_image_url_https" : "https://pbs.twimg.com/profile_images/427905238214144001/_QvjSvGl_normal.jpeg",
            "profile_link_color" : "0084B4",
            "profile_sidebar_border_color" : "C0DEED",
            "profile_sidebar_fill_color" : "DDEEF6",
            "profile_text_color" : "333333",
            "profile_use_background_image" : true,
            "protected" : false,
            "screen_name" : "josesalgado82",
            "statuses_count" : 1404,
            "time_zone" : "Madrid",
            "url" : null,
            "utc_offset" : 3600,
            "verified" : false
         }
      },
      {
         "contributors" : null,
         "coordinates" : null,
         "created_at" : "Wed Jan 29 19:47:00 +0000 2014",
         "entities" : {
            "hashtags" : [
               {
                  "indices" : [ 14, 28 ],
                  "text" : "SantaFeRental"
               }
            ],
            "symbols" : [],
            "urls" : [
               {
                  "display_url" : "bit.ly/192R8xQ",
                  "expanded_url" : "http://bit.ly/192R8xQ",
                  "indices" : [ 93, 115 ],
                  "url" : "http://t.co/6OLK7oLoAO"
               }
            ],
            "user_mentions" : []
         },
         "favorite_count" : 0,
         "favorited" : false,
         "geo" : null,
         "id" : 428615279547920384,
         "id_str" : "428615279547920384",
         "in_reply_to_screen_name" : null,
         "in_reply_to_status_id" : null,
         "in_reply_to_status_id_str" : null,
         "in_reply_to_user_id" : null,
         "in_reply_to_user_id_str" : null,
         "lang" : "en",
         "metadata" : {
            "iso_language_code" : "en",
            "result_type" : "recent"
         },
         "place" : null,
         "possibly_sensitive" : false,
         "retweet_count" : 0,
         "retweeted" : false,
         "source" : "<a href=\"http://sproutsocial.com\" rel=\"nofollow\">Sprout Social</a>",
         "text" : "Looking for a #SantaFeRental for you and your pet? Check out our list of pet friendly homes! http://t.co/6OLK7oLoAO",
         "truncated" : false,
         "user" : {
            "contributors_enabled" : false,
            "created_at" : "Tue Nov 16 22:43:07 +0000 2010",
            "default_profile" : false,
            "default_profile_image" : false,
            "description" : "Adobe Destinations, a division of Proctor Management, is a Santa Fe vacation rental company that specializes in luxury vacation rental accommodations.",
            "entities" : {
               "description" : {
                  "urls" : []
               },
               "url" : {
                  "urls" : [
                     {
                        "display_url" : "adobedestinations.com",
                        "expanded_url" : "http://www.adobedestinations.com",
                        "indices" : [ 0, 22 ],
                        "url" : "http://t.co/2w4qm7jw8Q"
                     }
                  ]
               }
            },
            "favourites_count" : 12,
            "follow_request_sent" : false,
            "followers_count" : 580,
            "following" : false,
            "friends_count" : 709,
            "geo_enabled" : false,
            "id" : 216509780,
            "id_str" : "216509780",
            "is_translation_enabled" : false,
            "is_translator" : false,
            "lang" : "en",
            "listed_count" : 13,
            "location" : "Santa Fe, New Mexico",
            "name" : "Adobe Destinations ",
            "notifications" : false,
            "profile_background_color" : "FFFFFF",
            "profile_background_image_url" : "http://a0.twimg.com/profile_background_images/222657116/freetwitterl-6--un-1-.br.jpg",
            "profile_background_image_url_https" : "https://si0.twimg.com/profile_background_images/222657116/freetwitterl-6--un-1-.br.jpg",
            "profile_background_tile" : false,
            "profile_banner_url" : "https://pbs.twimg.com/profile_banners/216509780/1364079366",
            "profile_image_url" : "http://pbs.twimg.com/profile_images/3420618389/84b421a695c0015b03c76f35d5320636_normal.jpeg",
            "profile_image_url_https" : "https://pbs.twimg.com/profile_images/3420618389/84b421a695c0015b03c76f35d5320636_normal.jpeg",
            "profile_link_color" : "383C2A",
            "profile_sidebar_border_color" : "000000",
            "profile_sidebar_fill_color" : "92818B",
            "profile_text_color" : "000000",
            "profile_use_background_image" : false,
            "protected" : false,
            "screen_name" : "irentsantafe",
            "statuses_count" : 704,
            "time_zone" : "Mountain Time (US & Canada)",
            "url" : "http://t.co/2w4qm7jw8Q",
            "utc_offset" : -25200,
            "verified" : false
         }
      },
      {
         "contributors" : null,
         "coordinates" : null,
         "created_at" : "Wed Jan 29 19:47:00 +0000 2014",
         "entities" : {
            "hashtags" : [],
            "symbols" : [],
            "urls" : [],
            "user_mentions" : [
               {
                  "id" : 303880286,
                  "id_str" : "303880286",
                  "indices" : [ 0, 10 ],
                  "name" : "Kengeworth",
                  "screen_name" : "Kenolabar"
               }
            ]
         },
         "favorite_count" : 0,
         "favorited" : false,
         "geo" : null,
         "id" : 428615278700687360,
         "id_str" : "428615278700687360",
         "in_reply_to_screen_name" : "Kenolabar",
         "in_reply_to_status_id" : 428615224199884800,
         "in_reply_to_status_id_str" : "428615224199884800",
         "in_reply_to_user_id" : 303880286,
         "in_reply_to_user_id_str" : "303880286",
         "lang" : "en",
         "metadata" : {
            "iso_language_code" : "en",
            "result_type" : "recent"
         },
         "place" : null,
         "retweet_count" : 0,
         "retweeted" : false,
         "source" : "<a href=\"http://janetter.net/\" rel=\"nofollow\">Janetter</a>",
         "text" : "@Kenolabar lol maybe",
         "truncated" : false,
         "user" : {
            "contributors_enabled" : false,
            "created_at" : "Sat Aug 07 01:12:15 +0000 2010",
            "default_profile" : false,
            "default_profile_image" : false,
            "description" : "Hyper-sexual bigendered bishonen princess, Reverse Trap, Lesbian, and gay man. I sing, dance and write poetry. #SWAG  #NSFW #FoolArcana Jailed: @GrimoireKaylyn",
            "entities" : {
               "description" : {
                  "urls" : []
               },
               "url" : {
                  "urls" : [
                     {
                        "display_url" : "gunstabwounds.tumblr.com/stabs",
                        "expanded_url" : "http://gunstabwounds.tumblr.com/stabs",
                        "indices" : [ 0, 22 ],
                        "url" : "http://t.co/fSp8Mo2Poa"
                     }
                  ]
               }
            },
            "favourites_count" : 430,
            "follow_request_sent" : false,
            "followers_count" : 1287,
            "following" : false,
            "friends_count" : 931,
            "geo_enabled" : true,
            "id" : 175586738,
            "id_str" : "175586738",
            "is_translation_enabled" : false,
            "is_translator" : false,
            "lang" : "en",
            "listed_count" : 39,
            "location" : "In Shadows Growing Wings",
            "name" : "King Kaylyn",
            "notifications" : false,
            "profile_background_color" : "E01BA2",
            "profile_background_image_url" : "http://a0.twimg.com/profile_background_images/378800000157974041/2f_T1di-.jpeg",
            "profile_background_image_url_https" : "https://si0.twimg.com/profile_background_images/378800000157974041/2f_T1di-.jpeg",
            "profile_background_tile" : true,
            "profile_banner_url" : "https://pbs.twimg.com/profile_banners/175586738/1387313070",
            "profile_image_url" : "http://pbs.twimg.com/profile_images/428077771122679808/aLV3q5Ax_normal.png",
            "profile_image_url_https" : "https://pbs.twimg.com/profile_images/428077771122679808/aLV3q5Ax_normal.png",
            "profile_link_color" : "ED3939",
            "profile_sidebar_border_color" : "000000",
            "profile_sidebar_fill_color" : "FF3D84",
            "profile_text_color" : "080808",
            "profile_use_background_image" : true,
            "protected" : false,
            "screen_name" : "Kayshire_Cat",
            "statuses_count" : 293700,
            "time_zone" : "Central Time (US & Canada)",
            "url" : "http://t.co/fSp8Mo2Poa",
            "utc_offset" : -21600,
            "verified" : false
         }
      },
      {
         "contributors" : null,
         "coordinates" : null,
         "created_at" : "Wed Jan 29 19:47:00 +0000 2014",
         "entities" : {
            "hashtags" : [],
            "symbols" : [],
            "urls" : [
               {
                  "display_url" : "youtu.be/yLGjmHHzA5M?a",
                  "expanded_url" : "http://youtu.be/yLGjmHHzA5M?a",
                  "indices" : [ 25, 47 ],
                  "url" : "http://t.co/Mrll8xjZAy"
               }
            ],
            "user_mentions" : [
               {
                  "id" : 10228272,
                  "id_str" : "10228272",
                  "indices" : [ 10, 18 ],
                  "name" : "YouTube",
                  "screen_name" : "YouTube"
               }
            ]
         },
         "favorite_count" : 0,
         "favorited" : false,
         "geo" : null,
         "id" : 428615278180974592,
         "id_str" : "428615278180974592",
         "in_reply_to_screen_name" : null,
         "in_reply_to_status_id" : null,
         "in_reply_to_status_id_str" : null,
         "in_reply_to_user_id" : null,
         "in_reply_to_user_id_str" : null,
         "lang" : "en",
         "metadata" : {
            "iso_language_code" : "en",
            "result_type" : "recent"
         },
         "place" : null,
         "possibly_sensitive" : false,
         "retweet_count" : 0,
         "retweeted" : false,
         "source" : "<a href=\"http://www.google.com/\" rel=\"nofollow\">Google</a>",
         "text" : "I liked a @YouTube video http://t.co/Mrll8xjZAy Wrecking Ball - Cat To Mouth - Bad Dub",
         "truncated" : false,
         "user" : {
            "contributors_enabled" : false,
            "created_at" : "Mon Aug 26 23:07:46 +0000 2013",
            "default_profile" : false,
            "default_profile_image" : false,
            "description" : "Youtuber and Minecraft player and well just #Boss  Also was known as the ipad kid at minecon I did interviews there!",
            "entities" : {
               "description" : {
                  "urls" : []
               },
               "url" : {
                  "urls" : [
                     {
                        "display_url" : "youtube.com/channel/UCX6gC…",
                        "expanded_url" : "http://www.youtube.com/channel/UCX6gCQKhD6vF2iO66m2geRQ",
                        "indices" : [ 0, 22 ],
                        "url" : "http://t.co/3bbVIVGxI6"
                     }
                  ]
               }
            },
            "favourites_count" : 23,
            "follow_request_sent" : false,
            "followers_count" : 62,
            "following" : false,
            "friends_count" : 284,
            "geo_enabled" : false,
            "id" : 1703126490,
            "id_str" : "1703126490",
            "is_translation_enabled" : false,
            "is_translator" : false,
            "lang" : "en",
            "listed_count" : 0,
            "location" : "",
            "name" : "NathansappPosgaming",
            "notifications" : false,
            "profile_background_color" : "C0DEED",
            "profile_background_image_url" : "http://a0.twimg.com/profile_background_images/378800000060325699/f1664a23b1b6f62867bd59fdc200d514.png",
            "profile_background_image_url_https" : "https://si0.twimg.com/profile_background_images/378800000060325699/f1664a23b1b6f62867bd59fdc200d514.png",
            "profile_background_tile" : false,
            "profile_image_url" : "http://pbs.twimg.com/profile_images/378800000366774271/31cf59b2fd9b13f38abfc1f1cb11b406_normal.png",
            "profile_image_url_https" : "https://pbs.twimg.com/profile_images/378800000366774271/31cf59b2fd9b13f38abfc1f1cb11b406_normal.png",
            "profile_link_color" : "0084B4",
            "profile_sidebar_border_color" : "FFFFFF",
            "profile_sidebar_fill_color" : "DDEEF6",
            "profile_text_color" : "333333",
            "profile_use_background_image" : true,
            "protected" : false,
            "screen_name" : "Posgaming",
            "statuses_count" : 2647,
            "time_zone" : "Eastern Time (US & Canada)",
            "url" : "http://t.co/3bbVIVGxI6",
            "utc_offset" : -18000,
            "verified" : false
         }
      },
      {
         "contributors" : null,
         "coordinates" : null,
         "created_at" : "Wed Jan 29 19:47:00 +0000 2014",
         "entities" : {
            "hashtags" : [],
            "symbols" : [],
            "urls" : [],
            "user_mentions" : [
               {
                  "id" : 587440727,
                  "id_str" : "587440727",
                  "indices" : [ 3, 14 ],
                  "name" : "Bethany Lister",
                  "screen_name" : "betalister"
               },
               {
                  "id" : 18783993,
                  "id_str" : "18783993",
                  "indices" : [ 37, 47 ],
                  "name" : "Meowski Catovitch",
                  "screen_name" : "catovitch"
               }
            ]
         },
         "favorite_count" : 0,
         "favorited" : false,
         "geo" : null,
         "id" : 428615277765750785,
         "id_str" : "428615277765750785",
         "in_reply_to_screen_name" : null,
         "in_reply_to_status_id" : null,
         "in_reply_to_status_id_str" : null,
         "in_reply_to_user_id" : null,
         "in_reply_to_user_id_str" : null,
         "lang" : "en",
         "metadata" : {
            "iso_language_code" : "en",
            "result_type" : "recent"
         },
         "place" : null,
         "retweet_count" : 5,
         "retweeted" : false,
         "retweeted_status" : {
            "contributors" : null,
            "coordinates" : null,
            "created_at" : "Wed Jan 29 17:48:47 +0000 2014",
            "entities" : {
               "hashtags" : [],
               "symbols" : [],
               "urls" : [],
               "user_mentions" : [
                  {
                     "id" : 18783993,
                     "id_str" : "18783993",
                     "indices" : [ 21, 31 ],
                     "name" : "Meowski Catovitch",
                     "screen_name" : "catovitch"
                  }
               ]
            },
            "favorite_count" : 4,
            "favorited" : false,
            "geo" : null,
            "id" : 428585529739730944,
            "id_str" : "428585529739730944",
            "in_reply_to_screen_name" : null,
            "in_reply_to_status_id" : null,
            "in_reply_to_status_id_str" : null,
            "in_reply_to_user_id" : null,
            "in_reply_to_user_id_str" : null,
            "lang" : "en",
            "metadata" : {
               "iso_language_code" : "en",
               "result_type" : "recent"
            },
            "place" : null,
            "retweet_count" : 5,
            "retweeted" : false,
            "source" : "<a href=\"https://about.twitter.com/products/tweetdeck\" rel=\"nofollow\">TweetDeck</a>",
            "text" : "We're all doomed! RT @catovitch: TIL: Cat tongues work on touch-screens.",
            "truncated" : false,
            "user" : {
               "contributors_enabled" : false,
               "created_at" : "Tue May 22 13:52:46 +0000 2012",
               "default_profile" : false,
               "default_profile_image" : false,
               "description" : "Nonprofit nerdist. Loves cats. Probably hungry.",
               "entities" : {
                  "description" : {
                     "urls" : []
                  }
               },
               "favourites_count" : 681,
               "follow_request_sent" : false,
               "followers_count" : 341,
               "following" : false,
               "friends_count" : 565,
               "geo_enabled" : true,
               "id" : 587440727,
               "id_str" : "587440727",
               "is_translation_enabled" : false,
               "is_translator" : false,
               "lang" : "en",
               "listed_count" : 29,
               "location" : "Portland, OR",
               "name" : "Bethany Lister",
               "notifications" : false,
               "profile_background_color" : "022330",
               "profile_background_image_url" : "http://abs.twimg.com/images/themes/theme15/bg.png",
               "profile_background_image_url_https" : "https://abs.twimg.com/images/themes/theme15/bg.png",
               "profile_background_tile" : false,
               "profile_banner_url" : "https://pbs.twimg.com/profile_banners/587440727/1376415330",
               "profile_image_url" : "http://pbs.twimg.com/profile_images/3334881890/e2c0da01fed9d4ff70d1d894c6ac0b75_normal.jpeg",
               "profile_image_url_https" : "https://pbs.twimg.com/profile_images/3334881890/e2c0da01fed9d4ff70d1d894c6ac0b75_normal.jpeg",
               "profile_link_color" : "0084B4",
               "profile_sidebar_border_color" : "A8C7F7",
               "profile_sidebar_fill_color" : "C0DFEC",
               "profile_text_color" : "333333",
               "profile_use_background_image" : true,
               "protected" : false,
               "screen_name" : "betalister",
               "statuses_count" : 2239,
               "time_zone" : "Pacific Time (US & Canada)",
               "url" : null,
               "utc_offset" : -28800,
               "verified" : false
            }
         },
         "source" : "web",
         "text" : "RT @betalister: We're all doomed! RT @catovitch: TIL: Cat tongues work on touch-screens.",
         "truncated" : false,
         "user" : {
            "contributors_enabled" : false,
            "created_at" : "Thu Aug 06 12:06:09 +0000 2009",
            "default_profile" : true,
            "default_profile_image" : false,
            "description" : "Recovering mathematician; juggler; aspiring climber and hacker.",
            "entities" : {
               "description" : {
                  "urls" : []
               },
               "url" : {
                  "urls" : [
                     {
                        "display_url" : "pozorvlak.livejournal.com",
                        "expanded_url" : "http://pozorvlak.livejournal.com",
                        "indices" : [ 0, 22 ],
                        "url" : "http://t.co/3cG39Kfplu"
                     }
                  ]
               }
            },
            "favourites_count" : 243,
            "follow_request_sent" : false,
            "followers_count" : 709,
            "following" : false,
            "friends_count" : 1064,
            "geo_enabled" : false,
            "id" : 63461288,
            "id_str" : "63461288",
            "is_translation_enabled" : false,
            "is_translator" : false,
            "lang" : "en",
            "listed_count" : 42,
            "location" : "Edinburgh",
            "name" : "Pozorvlak",
            "notifications" : false,
            "profile_background_color" : "C0DEED",
            "profile_background_image_url" : "http://abs.twimg.com/images/themes/theme1/bg.png",
            "profile_background_image_url_https" : "https://abs.twimg.com/images/themes/theme1/bg.png",
            "profile_background_tile" : false,
            "profile_image_url" : "http://pbs.twimg.com/profile_images/355112038/gasmask_normal.jpg",
            "profile_image_url_https" : "https://pbs.twimg.com/profile_images/355112038/gasmask_normal.jpg",
            "profile_link_color" : "0084B4",
            "profile_sidebar_border_color" : "C0DEED",
            "profile_sidebar_fill_color" : "DDEEF6",
            "profile_text_color" : "333333",
            "profile_use_background_image" : true,
            "protected" : false,
            "screen_name" : "pozorvlak",
            "statuses_count" : 30314,
            "time_zone" : "Amsterdam",
            "url" : "http://t.co/3cG39Kfplu",
            "utc_offset" : 3600,
            "verified" : false
         }
      },
      {
         "contributors" : null,
         "coordinates" : null,
         "created_at" : "Wed Jan 29 19:46:59 +0000 2014",
         "entities" : {
            "hashtags" : [],
            "symbols" : [],
            "urls" : [],
            "user_mentions" : []
         },
         "favorite_count" : 0,
         "favorited" : false,
         "geo" : null,
         "id" : 428615274871681024,
         "id_str" : "428615274871681024",
         "in_reply_to_screen_name" : null,
         "in_reply_to_status_id" : null,
         "in_reply_to_status_id_str" : null,
         "in_reply_to_user_id" : null,
         "in_reply_to_user_id_str" : null,
         "lang" : "en",
         "metadata" : {
            "iso_language_code" : "en",
            "result_type" : "recent"
         },
         "place" : null,
         "retweet_count" : 0,
         "retweeted" : false,
         "source" : "<a href=\"http://twitter.com/download/iphone\" rel=\"nofollow\">Twitter for iPhone</a>",
         "text" : "Niggas be getting cat fished off these social networks 😂",
         "truncated" : false,
         "user" : {
            "contributors_enabled" : false,
            "created_at" : "Sun Jun 06 16:00:32 +0000 2010",
            "default_profile" : false,
            "default_profile_image" : false,
            "description" : "West Philly",
            "entities" : {
               "description" : {
                  "urls" : []
               }
            },
            "favourites_count" : 97,
            "follow_request_sent" : false,
            "followers_count" : 612,
            "following" : false,
            "friends_count" : 568,
            "geo_enabled" : true,
            "id" : 152680300,
            "id_str" : "152680300",
            "is_translation_enabled" : false,
            "is_translator" : false,
            "lang" : "en",
            "listed_count" : 1,
            "location" : "",
            "name" : "O",
            "notifications" : false,
            "profile_background_color" : "030303",
            "profile_background_image_url" : "http://a0.twimg.com/profile_background_images/309815541/Love_Philly.jpg",
            "profile_background_image_url_https" : "https://si0.twimg.com/profile_background_images/309815541/Love_Philly.jpg",
            "profile_background_tile" : false,
            "profile_banner_url" : "https://pbs.twimg.com/profile_banners/152680300/1390982397",
            "profile_image_url" : "http://pbs.twimg.com/profile_images/428440578251300864/nCwmpZfc_normal.jpeg",
            "profile_image_url_https" : "https://pbs.twimg.com/profile_images/428440578251300864/nCwmpZfc_normal.jpeg",
            "profile_link_color" : "F5980C",
            "profile_sidebar_border_color" : "050404",
            "profile_sidebar_fill_color" : "131414",
            "profile_text_color" : "DB09DB",
            "profile_use_background_image" : true,
            "protected" : false,
            "screen_name" : "Oooo_Boy",
            "statuses_count" : 22525,
            "time_zone" : "Central Time (US & Canada)",
            "url" : null,
            "utc_offset" : -21600,
            "verified" : false
         }
      },
      {
         "contributors" : null,
         "coordinates" : null,
         "created_at" : "Wed Jan 29 19:46:59 +0000 2014",
         "entities" : {
            "hashtags" : [],
            "symbols" : [],
            "urls" : [
               {
                  "display_url" : "dailymail.co.uk/news/article-2…",
                  "expanded_url" : "http://www.dailymail.co.uk/news/article-2547823/The-woman-threw-pet-cat-gay.html",
                  "indices" : [ 12, 34 ],
                  "url" : "http://t.co/56nXV9x6c6"
               }
            ],
            "user_mentions" : [
               {
                  "id" : 23160845,
                  "id_str" : "23160845",
                  "indices" : [ 0, 11 ],
                  "name" : "Panti Bliss",
                  "screen_name" : "PantiBliss"
               }
            ]
         },
         "favorite_count" : 0,
         "favorited" : false,
         "geo" : null,
         "id" : 428615273663299584,
         "id_str" : "428615273663299584",
         "in_reply_to_screen_name" : "PantiBliss",
         "in_reply_to_status_id" : null,
         "in_reply_to_status_id_str" : null,
         "in_reply_to_user_id" : 23160845,
         "in_reply_to_user_id_str" : "23160845",
         "lang" : "und",
         "metadata" : {
            "iso_language_code" : "und",
            "result_type" : "recent"
         },
         "place" : null,
         "possibly_sensitive" : false,
         "retweet_count" : 0,
         "retweeted" : false,
         "source" : "web",
         "text" : "@PantiBliss http://t.co/56nXV9x6c6",
         "truncated" : false,
         "user" : {
            "contributors_enabled" : false,
            "created_at" : "Tue Jul 27 03:03:16 +0000 2010",
            "default_profile" : false,
            "default_profile_image" : false,
            "description" : "Loves science and space rockets. Already been to the Grand Canyon. An atheist.",
            "entities" : {
               "description" : {
                  "urls" : []
               }
            },
            "favourites_count" : 36,
            "follow_request_sent" : false,
            "followers_count" : 41,
            "following" : false,
            "friends_count" : 0,
            "geo_enabled" : false,
            "id" : 171329185,
            "id_str" : "171329185",
            "is_translation_enabled" : false,
            "is_translator" : false,
            "lang" : "en",
            "listed_count" : 1,
            "location" : "Liverpool",
            "name" : "glenn humphreys",
            "notifications" : false,
            "profile_background_color" : "FFF04D",
            "profile_background_image_url" : "http://abs.twimg.com/images/themes/theme19/bg.gif",
            "profile_background_image_url_https" : "https://abs.twimg.com/images/themes/theme19/bg.gif",
            "profile_background_tile" : false,
            "profile_banner_url" : "https://pbs.twimg.com/profile_banners/171329185/1384395081",
            "profile_image_url" : "http://pbs.twimg.com/profile_images/378800000795484175/97972d51f871877717c44ca2cb242fa5_normal.jpeg",
            "profile_image_url_https" : "https://pbs.twimg.com/profile_images/378800000795484175/97972d51f871877717c44ca2cb242fa5_normal.jpeg",
            "profile_link_color" : "0099CC",
            "profile_sidebar_border_color" : "FFF8AD",
            "profile_sidebar_fill_color" : "F6FFD1",
            "profile_text_color" : "333333",
            "profile_use_background_image" : true,
            "protected" : false,
            "screen_name" : "glennhumphreys",
            "statuses_count" : 2016,
            "time_zone" : "London",
            "url" : null,
            "utc_offset" : 0,
            "verified" : false
         }
      }
   ]
}

